auger_cli/__init__.py
auger_cli/cli.py
auger_cli/cli_client.py
auger_cli/client.py
auger_cli/config.py
auger_cli/constants.py
auger_cli/formatter.py
auger_cli/utils.py
auger_cli/api/__init__.py
auger_cli/api/auth.py
auger_cli/api/cluster_status.py
auger_cli/api/cluster_tasks.py
auger_cli/api/clusters.py
auger_cli/api/experiment_sessions.py
auger_cli/api/experiments.py
auger_cli/api/instance_types.py
auger_cli/api/orgs.py
auger_cli/api/pipeline_files.py
auger_cli/api/pipelines.py
auger_cli/api/predictions.py
auger_cli/api/projects.py
auger_cli/api/trials.py
auger_cli/commands/__init__.py
auger_cli/commands/auth.py
auger_cli/commands/cluster_status.py
auger_cli/commands/cluster_tasks.py
auger_cli/commands/clusters.py
auger_cli/commands/experiment_sessions.py
auger_cli/commands/experiments.py
auger_cli/commands/help.py
auger_cli/commands/instance_types.py
auger_cli/commands/orgs.py
auger_cli/commands/pipelines.py
auger_cli/commands/projects.py
auger_cli/commands/trials.py
auger_cli/logging/__init__.py
auger_cli/logging/pager.py
auger_cli/logging/stream.py
tests/api/__init__.py
tests/api/test_auth.py
tests/api/test_config.py
tests/api/test_experiments.py
tests/commands/__init__.py
tests/commands/test_auth.py
auger_cli-0.1.12.dist-info/LICENSE
auger_cli-0.1.12.dist-info/METADATA
auger_cli-0.1.12.dist-info/WHEEL
auger_cli-0.1.12.dist-info/entry_points.txt
auger_cli-0.1.12.dist-info/top_level.txt
auger_cli-0.1.12.dist-info/RECORD
