Metadata-Version: 2.1
Name: auger-cli
Version: 0.1.12
Summary: Command line tool for the Auger AI platform.
Home-page: https://github.com/deeplearninc/auger-cli
Author: Auger AI
License: MIT
Keywords: augerai auger ai machine learning automl deeplearn api sdk
Platform: any
Classifier: Development Status :: 3 - Alpha
Classifier: Intended Audience :: Developers
Classifier: Intended Audience :: System Administrators
Classifier: Topic :: Software Development :: Build Tools
Classifier: License :: OSI Approved :: MIT License
Classifier: Programming Language :: Python :: 3
Classifier: Programming Language :: Python :: 3.6
Classifier: Programming Language :: Python :: 3.7
Classifier: Programming Language :: Python :: 3 :: Only
Requires-Python: >=3
Requires-Dist: click (>=6.7)
Requires-Dist: click-spinner (>=0.1)
Requires-Dist: auger-hub-api-client (>=0.5.6)
Requires-Dist: pandas (==0.23.4)
Requires-Dist: ruamel.yaml
